azureml/__init__.py
azureml/assets/__init__.py
azureml/assets/asset_utils.py
azureml/assets/config.py
azureml/assets/copy_assets.py
azureml/assets/deployment_config.py
azureml/assets/extract_tagged_assets.py
azureml/assets/get_tokens.py
azureml/assets/publish_utils.py
azureml/assets/tag_released_assets.py
azureml/assets/update_assets.py
azureml/assets/update_spec.py
azureml/assets/validate_assets.py
azureml/assets/validate_tree.py
azureml/assets/config/supported_inference_skus.json
azureml/assets/config/tag_values_prompt.yaml
azureml/assets/config/tag_values_shared.yaml
azureml/assets/config/evaluationresult/tag_values_shared.yaml
azureml/assets/config/evaluationresult/tag_values_text_cost.yaml
azureml/assets/config/evaluationresult/tag_values_text_embeddings.yaml
azureml/assets/config/evaluationresult/tag_values_text_generation.yaml
azureml/assets/config/evaluationresult/tag_values_text_performance.yaml
azureml/assets/config/evaluationresult/tag_values_text_quality.yaml
azureml/assets/config/evaluationresult/tag_values_vision.yaml
azureml/assets/environment/__init__.py
azureml/assets/environment/build.py
azureml/assets/environment/pin_image_versions.py
azureml/assets/environment/pin_package_versions.py
azureml/assets/environment/pin_versions.py
azureml/assets/environment/validate_build_logs.py
azureml/assets/model/__init__.py
azureml/assets/model/download_utils.py
azureml/assets/model/registry_utils.py
azureml/assets/util/__init__.py
azureml/assets/util/logger.py
azureml/assets/util/sku_utils.py
azureml/assets/util/template.py
azureml/assets/util/util.py
azureml_assets-1.16.102.dist-info/METADATA
azureml_assets-1.16.102.dist-info/WHEEL
azureml_assets-1.16.102.dist-info/top_level.txt
azureml_assets-1.16.102.dist-info/RECORD
