Metadata-Version: 2.4
Name: azureml-assets
Version: 1.16.102
Summary: Utilities for publishing assets to Azure Machine Learning system registries.
Author: Microsoft Corp
License: MIT
Project-URL: Source, https://github.com/Azure/azureml-assets/
Project-URL: Changelog, https://github.com/Azure/azureml-assets/blob/main/scripts/azureml-assets/CHANGELOG.md
Classifier: Development Status :: 5 - Production/Stable
Classifier: Intended Audience :: Developers
Classifier: Topic :: Software Development :: Build Tools
Classifier: License :: OSI Approved :: MIT License
Classifier: Programming Language :: Python :: 3.8
Classifier: Programming Language :: Python :: 3.9
Classifier: Programming Language :: Python :: 3.10
Classifier: Programming Language :: Python :: 3.11
Requires-Python: >=3.8,<4.0
Requires-Dist: GitPython>=3.1
Requires-Dist: ruamel.yaml~=0.18.10
Requires-Dist: pip>=21
Requires-Dist: marshmallow>=3.19
Requires-Dist: tenacity>=8.2.2
Requires-Dist: azure-ai-ml>=1.9.0
Requires-Dist: azure-identity>=1.16.0
Dynamic: author
Dynamic: classifier
Dynamic: license
Dynamic: project-url
Dynamic: requires-dist
Dynamic: requires-python
Dynamic: summary
